CHANGES.md
MANIFEST.in
README.md
setup.py
onetsdb/__init__.py
onetsdb/base.py
onetsdb/influx.py
onetsdb/mongo.py
onetsdb/sqlite.py
onetsdb/xtslite.py
onetsdb.egg-info/PKG-INFO
onetsdb.egg-info/SOURCES.txt
onetsdb.egg-info/dependency_links.txt
onetsdb.egg-info/not-zip-safe
onetsdb.egg-info/requires.txt
onetsdb.egg-info/top_level.txt