Metadata-Version: 2.1
Name: onetsdb
Version: 1.3.0
Summary: A Uniform Interface for Timeseries Database Python Library.
Home-page: https://github.com/sintrb/onetsdb/
Author: trb
Author-email: sintrb@gmail.com
License: UNKNOWN
Keywords: TSDB,MongoDB,InfluxDB,NoSQL,Sqlite3,tslite,Time Series Database
Platform: UNKNOWN
